{
  "panel.build": "Proje Derle",
  "panel.console": "Konsol",
  "panel.environment": "Ortam",
  "panel.game": "Oyun",
  "panel.hierarchy": "Hiyerarsi",
  "panel.inspector": "Denetleyici",
  "panel.orm_packer": "ORM Packer",
  "panel.preferences": "Tercihler",
  "panel.project": "Proje",
  "panel.project_settings": "Proje Ayarlari",
  "panel.scene": "Sahne",

  "save.auto_saved": "Otomatik kaydedildi",
  "save.cant_play_mode": "Oyun modunda kaydedilemez",
  "save.cant_play_mode_msg": "Sahne, prefab veya grafi kaydetmek icin oyun modundan cikin.",
  "save.graph": "Graf: {{name}}",
  "save.layout": "Editor Duzeni",
  "save.nothing": "Kaydedilecek bir sey yok",
  "save.nothing_msg": "Tum dosyalar guncel.",
  "save.prefab": "Prefab: {{name}}",
  "save.saved": "Kaydedildi",
  "save.scene": "Sahne: {{name}}",

  "dialog.delete_assets": "Varliklari Sil",

  "hierarchy.delete": "Sil",
  "hierarchy.duplicate": "Cogalt",
  "hierarchy.rename": "Yeniden Adlandir",

  "project.copy_path": "Yolu Kopyala",
  "project.delete": "Sil",
  "project.reimport": "Yeniden Ice Aktar",
  "project.rename": "Yeniden Adlandir",
  "project.show_in_explorer": "Gezginde Goster",

  "toast.cursor_locked": "Imlec Kilitlendi",
  "toast.cursor_locked_msg": "Serbest birakmak icin Escape'e basin.",
  "toast.cursor_lock_failed": "Imlec Kilitleme Basarisiz",
  "toast.cursor_lock_failed_msg": "Gecerli bir oyun gorunumu yok.",
  "toast.prefab_structure": "Prefab Yapisi",
  "toast.prefab_cant_add": "Bir prefab ornegine alt nesne eklenemez. Once prefabi kirin.",
  "toast.prefab_cant_delete": "Bir prefab alt nesnesi silinemez. Once prefabi kirin.",
  "toast.prefab_cant_move": "Bir prefab alt nesnesi tasinamaz. Once prefabi kirin.",
  "toast.rename_exists": "'{{name}}' adinda bir dosya veya klasor zaten mevcut.",
  "toast.rename_failed": "Yeniden Adlandirma Basarisiz",

  "console.clear": "Temizle",
  "console.collapse": "Grupla",
  "console.filter": "Filtrele...",
  "console.log_tests": "Log Testleri",
  "console.log": "Log",
  "console.log_warning": "LogUyari",
  "console.log_error": "LogHata",
  "console.log_success": "LogBasari",
  "console.show_time": "Zamani Goster",
  "console.multi_line": "Cok Satirli",

  "launcher.search": "Proje ara",
  "launcher.open_project": "Proje ac",
  "launcher.new_project": "Yeni proje",
  "launcher.name": "Ad:",
  "launcher.path": "Yol:",
  "launcher.create": "Olustur",
  "launcher.no_recent": "Son proje yok",
  "launcher.hint": "Baslamak icin yeni bir proje olusturun veya mevcut birini acin.",
  "launcher.invalid_name": "Gecersiz ad",
  "launcher.name_empty": "Proje adi bos olamaz.",
  "launcher.folder_exists": "Klasor mevcut",
  "launcher.folder_exists_msg": "'{{name}}' zaten mevcut ve bos degil. Farkli bir ad veya konum secin.",
  "launcher.create_failed": "Olusturma basarisiz",
  "launcher.open_failed": "Proje acilamadi: {{message}}",
  "launcher.just_now": "Az once",
  "launcher.minutes_ago": "{{count}}dk once",
  "launcher.hours_ago": "{{count}}sa once",
  "launcher.days_ago": "{{count}}g once",
  "launcher.months_ago": "{{count}}ay once",
  "launcher.years_ago": "{{count}}yil once",
  "launcher.missing": "Eksik",

  "inspector.nothing_selected": "Hicbir sey secilmedi",
  "inspector.nothing_selected_hint": "Incelemek icin bir varlik veya nesne secin.",
  "inspector.selection": "Secim",
  "inspector.objects_selected": "nesne secili",
  "inspector.and_more": "... ve {{count}} tane daha",
  "inspector.folder": "Klasor",
  "inspector.path": "Yol",
  "inspector.files": "Dosyalar",
  "inspector.subfolders": "Alt klasorler",
  "inspector.sub_asset": "Alt Varlik",
  "inspector.type": "Tur",
  "inspector.parent": "Ust",
  "inspector.size": "Boyut",
  "inspector.format": "Format",
  "inspector.properties_readonly": "Ozellikler (Salt okunur)",
  "inspector.extract_as_asset": "Varlik olarak cikar",
  "inspector.asset_info": "Varlik Bilgisi",
  "inspector.importer": "Iceaktarici",
  "inspector.modified": "Degistirilme",
  "inspector.dependencies": "Bagimliliklar",
  "inspector.used_by": "Kullanan",
  "inspector.import_settings": "Iceaktarma Ayarlari",
  "inspector.save_and_reimport": "Kaydet ve Yeniden Ice Aktar",
  "inspector.reimport": "Yeniden Ice Aktar",
  "inspector.name": "Ad",
  "inspector.instance_id": "Ornek ID",
  "inspector.asset_id": "Varlik ID",
  "inspector.asset_path": "Varlik Yolu",
  "inspector.properties": "Ozellikler",
  "inspector.time": "Zaman",
  "inspector.count": "Sayi",
  "inspector.message": "Mesaj",
  "inspector.stack_trace": "Yigin Izleme",

  "menu.file": "Dosya",
  "menu.file.new_scene": "Yeni Sahne",
  "menu.file.open_scene": "Sahne Ac",
  "menu.file.save_scene": "Sahneyi Kaydet",
  "menu.file.save_scene_as": "Sahneyi Farkli Kaydet...",
  "menu.file.open_project": "Proje Ac...",
  "menu.file.build_project": "Proje Derle...",
  "menu.file.exit": "Cikis",
  "menu.edit": "Duzenle",
  "menu.edit.undo": "Geri Al",
  "menu.edit.redo": "Yinele",
  "menu.edit.project_settings": "Proje Ayarlari...",
  "menu.edit.save_layout": "Duzeni Kaydet",
  "menu.edit.preferences": "Tercihler...",
  "menu.assets": "Varliklar",
  "menu.assets.import_package": "Paket Ice Aktar...",
  "menu.assets.create_folder": "Klasor Olustur",
  "menu.assets.create_shader": "Shader Olustur",
  "menu.assets.create_script": "C# Betik Olustur",
  "menu.assets.refresh": "Yenile",
  "menu.assets.reimport_all": "Tumunu Yeniden Ice Aktar",

  "hierarchy.back": "Geri",
  "hierarchy.save_and_exit": "Kaydet ve Cik",
  "hierarchy.no_scene_loaded": "Sahne yuklenmedi",
  "hierarchy.new_scene": "Yeni sahne",
  "hierarchy.drop_to_spawn": "Olusturmak icin birakin",
  "hierarchy.scene_empty": "Sahne bos",
  "hierarchy.move_to_view": "Gorunume tasi",
  "hierarchy.move_view_to": "Gorunumu tasi",
  "hierarchy.select_prefab_asset": "Prefab varligini sec",
  "hierarchy.apply_prefab_overrides": "Prefab degisikliklerini uygula",
  "hierarchy.revert_to_prefab": "Prefab'a geri don",
  "hierarchy.break_prefab_instance": "Prefab baglantisini kopar",
  "hierarchy.disable_all": "Tumunu devre disi birak",
  "hierarchy.enable_all": "Tumunu etkinlestir",
  "hierarchy.disable": "Devre disi birak",
  "hierarchy.enable": "Etkinlestir",

  "inspector.static": "Statik",
  "inspector.tag": "Etiket",
  "inspector.layer": "Katman",
  "inspector.transform": "Transform",
  "inspector.position": "Konum",
  "inspector.rotation": "Donus",
  "inspector.scale": "Olcek",
  "inspector.add_component": "Bilesen ekle",
  "inspector.reset": "Sifirla",
  "inspector.remove_component": "Bileseni kaldir",
  "inspector.move_up": "Yukari tasi",
  "inspector.move_down": "Asagi tasi",
  "inspector.pop_out": "Ayir",
  "inspector.select": "Sec",
  "inspector.revert": "Geri al",
  "inspector.apply": "Uygula",
  "inspector.missing_prefab": "Prefab bulunamadi!",
  "inspector.missing": "Eksik",
  "inspector.nested_prefab": "Ic ice Prefab: {{name}}",
  "inspector.prefab": "Prefab: {{name}}"
}
